{
  "db": "PostgreSQL",
  "c356e2049752b514ff9c4c9eef664f7de625d4e610f97ed820c4f50819a3c208": {
    "describe": {
      "columns": [
        {
          "name": "email",
          "ordinal": 0,
          "type_info": "Text"
        },
        {
          "name": "username",
          "ordinal": 1,
          "type_info": "Varchar"
        }
      ],
      "nullable": [
        false,
        false
      ],
      "parameters": {
        "Left": [
          "Text",
          "Text"
        ]
      }
    },
    "query": "SELECT email, username FROM play_user WHERE (email = $1) OR (username = $2)"
  },
  "831e114c9ed25e6af20bf1c039fbe4485d26add0ac2bd03994ad484c6a500ec3": {
    "describe": {
      "columns": [],
      "nullable": [],
      "parameters": {
        "Left": [
          "Text",
          "Varchar",
          "Text"
        ]
      }
    },
    "query": "INSERT INTO play_user (email, username, hash) VALUES ($1, $2, $3)"
  }
}